[
  {
    "id": "Jh1YAFPQ9rk",
    "title": "2026 剪輯工具推薦：六款軟體優缺點、硬體需求一次看清",
    "desc": "歡迎來到Nash Wu 的頻道！   2026 年，剪影片已經是每個人的標配技能，但市面上剪輯軟體這麼多，到底哪一款最安全、最適合你 ...",
    "thumbnail": "https://i.ytimg.com/vi/Jh1YAFPQ9rk/hqdefault.jpg",
    "url": "https://www.youtube.com/watch?v=Jh1YAFPQ9rk"
  },
  {
    "id": "Lyncas2766k",
    "title": "The first trip in 2026.#Insta360awards #Insta360LeicaAwards #insta360 ace pro2 #ShotOnInsta360",
    "desc": "",
    "thumbnail": "https://i.ytimg.com/vi/Lyncas2766k/hqdefault.jpg",
    "url": "https://www.youtube.com/watch?v=Lyncas2766k"
  },
  {
    "id": "oVdVDXjel1k",
    "title": "【2025 終局之戰】從手機成癮到找回專注力 ⚡️ 我的 2026 年度計畫！",
    "desc": "歡迎來到Nash Wu 的頻道！   重點在於「成長」與「專注」，能吸引想提升自我效率的觀眾。 2026年的第一個假日，我想和大家聊 ...",
    "thumbnail": "https://i.ytimg.com/vi/oVdVDXjel1k/hqdefault.jpg",
    "url": "https://www.youtube.com/watch?v=oVdVDXjel1k"
  },
  {
    "id": "RIwyAb1FMUM",
    "title": "零基礎也能變高手！VN 剪輯秘訣、字體+濾鏡全攻略",
    "desc": "歡迎來到Nash Wu 的頻道！   你是不是也覺得剪輯很難、很花時間？別擔心，今天這支影片就要帶你用VN 剪輯App，從完全的『零 ...",
    "thumbnail": "https://i.ytimg.com/vi/RIwyAb1FMUM/hqdefault.jpg",
    "url": "https://www.youtube.com/watch?v=RIwyAb1FMUM"
  },
  {
    "id": "pb8SNr0_YTk",
    "title": "解密 Vibe Coding：原理、應用與操作指南搭配最新的Gemini 3 Pro",
    "desc": "歡迎來到Nash Wu 的頻道！   厭倦了繁瑣的程式碼撰寫？Vibe Coding 或許能為你帶來全新的體驗！這份「解密Vibe Coding」的 ...",
    "thumbnail": "https://i.ytimg.com/vi/pb8SNr0_YTk/hqdefault.jpg",
    "url": "https://www.youtube.com/watch?v=pb8SNr0_YTk"
  },
  {
    "id": "q2aDNzGwRNA",
    "title": "在新竹數位實驗高中的一天",
    "desc": "歡迎來到Nash Wu 的頻道！   我的高中生活小小記錄~ 這是一個分享生活點滴、深度旅遊體驗與最新科技產品的頻道。",
    "thumbnail": "https://i.ytimg.com/vi/q2aDNzGwRNA/hqdefault.jpg",
    "url": "https://www.youtube.com/watch?v=q2aDNzGwRNA"
  }
]